evosax/__init__.py
evosax/types.py
evosax/algorithms/__init__.py
evosax/algorithms/base.py
evosax/algorithms/ckpt/__init__.py
evosax/algorithms/ckpt/evotf/2024_03_SNES_small.pkl
evosax/algorithms/ckpt/les/2023_03_les_v1.pkl
evosax/algorithms/ckpt/les/2023_10_les_v2.pkl
evosax/algorithms/ckpt/lga/2023_04_lga_v4.pkl
evosax/algorithms/ckpt/lga/2023_04_lga_v7.pkl
evosax/algorithms/distribution_based/__init__.py
evosax/algorithms/distribution_based/ars.py
evosax/algorithms/distribution_based/asebo.py
evosax/algorithms/distribution_based/base.py
evosax/algorithms/distribution_based/cma_es.py
evosax/algorithms/distribution_based/cr_fm_nes.py
evosax/algorithms/distribution_based/discovered_es.py
evosax/algorithms/distribution_based/esmc.py
evosax/algorithms/distribution_based/evotf_es.py
evosax/algorithms/distribution_based/gradientless_descent.py
evosax/algorithms/distribution_based/guided_es.py
evosax/algorithms/distribution_based/hill_climbing.py
evosax/algorithms/distribution_based/iamalgam_full.py
evosax/algorithms/distribution_based/iamalgam_univariate.py
evosax/algorithms/distribution_based/learned_es.py
evosax/algorithms/distribution_based/lm_ma_es.py
evosax/algorithms/distribution_based/ma_es.py
evosax/algorithms/distribution_based/noise_reuse_es.py
evosax/algorithms/distribution_based/open_es.py
evosax/algorithms/distribution_based/persistent_es.py
evosax/algorithms/distribution_based/pgpe.py
evosax/algorithms/distribution_based/random_search.py
evosax/algorithms/distribution_based/rm_es.py
evosax/algorithms/distribution_based/sep_cma_es.py
evosax/algorithms/distribution_based/simple_es.py
evosax/algorithms/distribution_based/simulated_annealing.py
evosax/algorithms/distribution_based/snes.py
evosax/algorithms/distribution_based/xnes.py
evosax/algorithms/distribution_based/sv/__init__.py
evosax/algorithms/distribution_based/sv/base.py
evosax/algorithms/distribution_based/sv/sv_cma_es.py
evosax/algorithms/distribution_based/sv/sv_open_es.py
evosax-0.2.0.dist-info/METADATA
evosax-0.2.0.dist-info/WHEEL
evosax-0.2.0.dist-info/top_level.txt
evosax-0.2.0.dist-info/RECORD
