Metadata-Version: 2.2
Name: evosax
Version: 0.2.0
Summary: Evolution Strategies in JAX
Author-email: Robert Tjarko Lange <robertlange0@gmail.com>
License: Apache-2.0
Project-URL: Homepage, https://github.com/RobertTLange/evosax
Keywords: evolution-strategy,evolutionary-algorithms,neuroevolution
Classifier: Programming Language :: Python :: 3.10
Classifier: Programming Language :: Python :: 3.11
Classifier: Programming Language :: Python :: 3.12
Classifier: Programming Language :: Python :: 3.13
Classifier: License :: OSI Approved :: Apache Software License
Classifier: Operating System :: OS Independent
Classifier: Topic :: Scientific/Engineering :: Artificial Intelligence
Requires-Python: >=3.10
Requires-Dist: numpy>=1.25
Requires-Dist: jax>=0.5.0
Requires-Dist: flax>=0.10.0
Requires-Dist: dotmap
Requires-Dist: matplotlib
Provides-Extra: dev
Requires-Dist: pytest>=8.3.2; extra == "dev"
Requires-Dist: pytest-cov>=5.0.0; extra == "dev"
Requires-Dist: ruff>=0.6.4; extra == "dev"
Requires-Dist: mypy>=1.11.2; extra == "dev"
Provides-Extra: examples
Requires-Dist: torch; extra == "examples"
Requires-Dist: torchvision; extra == "examples"
Requires-Dist: brax; extra == "examples"
Requires-Dist: gymnax; extra == "examples"
Requires-Dist: ipykernel; extra == "examples"
